[
  {
    "fraudulent": 1,
    "job_title": "مدرس",
    "job_date": "29/05/1444",
    "job_desc": "['فرصة ذهبية للعمل في بيئة احترافية.']",
    "job_tasks": "['   متابعة البريد', '   إعداد تقارير', '   الرد على مكالمات', '  ', '  ']",
    "comp_name": "شركة المال السهل",
    "comp_no": "9-491849",
    "comp_type": "حكومي سري",
    "comp_size": "كبيرة",
    "eco_activity": "nan",
    "qualif": "شهادة ثانوية",
    "region": "المدينة المنورة",
    "city": "AR RIYADH...",
    "benefits": "['Salary','10000']",
    "contract": "عقد مؤقت",
    "positions": "0 / 19",
    "job_post_id": "FRAUD2025QUAL1000",
    "exper": "5 Years"
  },
  {
    "fraudulent": 1,
    "job_title": "مدرس",
    "job_date": "27/05/1444",
    "job_desc": "['راتب عالي جدا بدون أي متطلبات إضافية.']",
    "job_tasks": "['   الرد على رسائل واتساب', '   حفظ ملفات بسيطة', '  ', '  ']",
    "comp_name": "شركة الثروة السريعة",
    "comp_no": "4-959071",
    "comp_type": "غير ربحي",
    "comp_size": "صغيرة فئة أ",
    "eco_activity": "nan",
    "qualif": "ثانوية عامة",
    "region": "مكة المكرمة",
    "city": "AD DAMMAM...",
    "benefits": "['Salary','30000']",
    "contract": "دوام كامل",
    "positions": "0 / 13",
    "job_post_id": "FRAUD2025QUAL1001",
    "exper": "3 Years"
  },
  {
    "fraudulent": 1,
    "job_title": "مدير تنفيذي",
    "job_date": "27/05/1444",
    "job_desc": "['راتب عالي جدا بدون أي متطلبات إضافية.']",
    "job_tasks": "['   متابعة البريد', '   إعداد تقارير', '   الرد على مكالمات', '  ', '  ']",
    "comp_name": "جهة حكومية سرية",
    "comp_no": "9-329074",
    "comp_type": "حكومي سري",
    "comp_size": "صغيرة فئة أ",
    "eco_activity": "nan",
    "qualif": "ثانوية عامة",
    "region": "المنطقة الشرقية",
    "city": "AD DAMMAM...",
    "benefits": "['Salary','30000']",
    "contract": "دوام كامل",
    "positions": "0 / 34",
    "job_post_id": "FRAUD2025QUAL1002",
    "exper": "3 Years"
  },
  {
    "fraudulent": 1,
    "job_title": "طبيب أسنان",
    "job_date": "30/05/1444",
    "job_desc": "['راتب عالي جدا بدون أي متطلبات إضافية.']",
    "job_tasks": "['   كتابة محتوى', '   تصميم بسيط', '   رفع تقارير دورية', '  ', '  ']",
    "comp_name": "شركة المال السهل",
    "comp_no": "9-704894",
    "comp_type": "خاص",
    "comp_size": "كبيرة",
    "eco_activity": "nan",
    "qualif": "Diploma",
    "region": "المنطقة الشرقية",
    "city": "JEDDAH...",
    "benefits": "['Salary','30000']",
    "contract": "عقد مؤقت",
    "positions": "0 / 26",
    "job_post_id": "FRAUD2025QUAL1003",
    "exper": "0 Years"
  },
  {
    "fraudulent": 1,
    "job_title": "طبيب أسنان",
    "job_date": "29/05/1444",
    "job_desc": "['راتب عالي جدا بدون أي متطلبات إضافية.']",
    "job_tasks": "['   الرد على رسائل واتساب', '   حفظ ملفات بسيطة', '  ', '  ']",
    "comp_name": "جهة حكومية سرية",
    "comp_no": "3-415138",
    "comp_type": "غير ربحي",
    "comp_size": "متوسطة فئة أ",
    "eco_activity": "nan",
    "qualif": "شهادة ابتدائية",
    "region": "المنطقة الشرقية",
    "city": "JEDDAH...",
    "benefits": "['Salary','10000']",
    "contract": "دوام كامل",
    "positions": "0 / 30",
    "job_post_id": "FRAUD2025QUAL1004",
    "exper": "0 Years"
  },
  {
    "fraudulent": 1,
    "job_title": "محلل مالي",
    "job_date": "30/05/1444",
    "job_desc": "['عمل إداري بسيط لا يتطلب مؤهلات خاصة.']",
    "job_tasks": "['   الرد على رسائل واتساب', '   حفظ ملفات بسيطة', '  ', '  ']",
    "comp_name": "مؤسسة النجاح الفوري",
    "comp_no": "2-776664",
    "comp_type": "خاص",
    "comp_size": "كبيرة",
    "eco_activity": "nan",
    "qualif": "ثانوية عامة",
    "region": "المنطقة الشرقية",
    "city": "AL MADINAH...",
    "benefits": "['Salary','10000']",
    "contract": "دوام كامل",
    "positions": "0 / 29",
    "job_post_id": "FRAUD2025QUAL1005",
    "exper": "1 Years"
  },
  {
    "fraudulent": 1,
    "job_title": "طبيب عام",
    "job_date": "29/05/1444",
    "job_desc": "['وظيفة حكومية مرموقة - الرجاء إرسال السيرة عبر الجيميل.']",
    "job_tasks": "['   الرد على رسائل واتساب', '   حفظ ملفات بسيطة', '  ', '  ']",
    "comp_name": "جهة حكومية سرية",
    "comp_no": "4-791446",
    "comp_type": "غير ربحي",
    "comp_size": "متوسطة فئة أ",
    "eco_activity": "nan",
    "qualif": "Diploma",
    "region": "المدينة المنورة",
    "city": "AD DAMMAM...",
    "benefits": "['Salary','15000']",
    "contract": "دوام جزئي",
    "positions": "0 / 21",
    "job_post_id": "FRAUD2025QUAL1006",
    "exper": "3 Years"
  },
  {
    "fraudulent": 1,
    "job_title": "مطور ويب",
    "job_date": "29/05/1444",
    "job_desc": "['وظيفة حكومية مرموقة - الرجاء إرسال السيرة عبر الجيميل.']",
    "job_tasks": "['   كتابة محتوى', '   تصميم بسيط', '   رفع تقارير دورية', '  ', '  ']",
    "comp_name": "مؤسسة النجاح الفوري",
    "comp_no": "8-458884",
    "comp_type": "حكومي سري",
    "comp_size": "كبيرة",
    "eco_activity": "nan",
    "qualif": "شهادة ابتدائية",
    "region": "مكة المكرمة",
    "city": "AR RIYADH...",
    "benefits": "['Salary','20000']",
    "contract": "دوام جزئي",
    "positions": "0 / 10",
    "job_post_id": "FRAUD2025QUAL1007",
    "exper": "5 Years"
  },
  {
    "fraudulent": 1,
    "job_title": "مهندس برمجيات",
    "job_date": "29/05/1444",
    "job_desc": "['راتب عالي جدا بدون أي متطلبات إضافية.']",
    "job_tasks": "['   كتابة محتوى', '   تصميم بسيط', '   رفع تقارير دورية', '  ', '  ']",
    "comp_name": "شركة المال السهل",
    "comp_no": "2-499384",
    "comp_type": "غير ربحي",
    "comp_size": "متوسطة فئة أ",
    "eco_activity": "nan",
    "qualif": "شهادة متوسطة",
    "region": "المدينة المنورة",
    "city": "AL MADINAH...",
    "benefits": "['Salary','40000']",
    "contract": "عقد مؤقت",
    "positions": "0 / 34",
    "job_post_id": "FRAUD2025QUAL1008",
    "exper": "3 Years"
  },
  {
    "fraudulent": 1,
    "job_title": "مطور ويب",
    "job_date": "30/05/1444",
    "job_desc": "['فرصة ذهبية للعمل في بيئة احترافية.']",
    "job_tasks": "['   متابعة البريد', '   إعداد تقارير', '   الرد على مكالمات', '  ', '  ']",
    "comp_name": "شركة الثروة السريعة",
    "comp_no": "6-206185",
    "comp_type": "خاص",
    "comp_size": "صغيرة فئة أ",
    "eco_activity": "nan",
    "qualif": "شهادة ثانوية",
    "region": "المدينة المنورة",
    "city": "AL MADINAH...",
    "benefits": "['Salary','20000']",
    "contract": "دوام كامل",
    "positions": "0 / 13",
    "job_post_id": "FRAUD2025QUAL1009",
    "exper": "0 Years"
  },
  {
    "fraudulent": 1,
    "job_title": "محلل مالي",
    "job_date": "30/05/1444",
    "job_desc": "['مطلوب فورا - التواصل عبر الواتساب فقط.']",
    "job_tasks": "['   الرد على رسائل واتساب', '   حفظ ملفات بسيطة', '  ', '  ']",
    "comp_name": "شركة الثروة السريعة",
    "comp_no": "6-281168",
    "comp_type": "حكومي سري",
    "comp_size": "كبيرة",
    "eco_activity": "nan",
    "qualif": "ثانوية عامة",
    "region": "مكة المكرمة",
    "city": "JEDDAH...",
    "benefits": "['Salary','15000']",
    "contract": "عقد مؤقت",
    "positions": "0 / 5",
    "job_post_id": "FRAUD2025QUAL1010",
    "exper": "1 Years"
  },
  {
    "fraudulent": 1,
    "job_title": "محاسب",
    "job_date": "29/05/1444",
    "job_desc": "['راتب عالي جدا بدون أي متطلبات إضافية.']",
    "job_tasks": "['   الرد على رسائل واتساب', '   حفظ ملفات بسيطة', '  ', '  ']",
    "comp_name": "جهة حكومية سرية",
    "comp_no": "5-624317",
    "comp_type": "غير ربحي",
    "comp_size": "صغيرة فئة أ",
    "eco_activity": "nan",
    "qualif": "شهادة ابتدائية",
    "region": "المدينة المنورة",
    "city": "AR RIYADH...",
    "benefits": "['Salary','10000']",
    "contract": "دوام جزئي",
    "positions": "0 / 13",
    "job_post_id": "FRAUD2025QUAL1011",
    "exper": "3 Years"
  },
  {
    "fraudulent": 1,
    "job_title": "محامي",
    "job_date": "29/05/1444",
    "job_desc": "['فرصة ذهبية للعمل في بيئة احترافية.']",
    "job_tasks": "['   كتابة محتوى', '   تصميم بسيط', '   رفع تقارير دورية', '  ', '  ']",
    "comp_name": "جهة حكومية سرية",
    "comp_no": "9-498588",
    "comp_type": "خاص",
    "comp_size": "متوسطة فئة أ",
    "eco_activity": "nan",
    "qualif": "شهادة ابتدائية",
    "region": "المدينة المنورة",
    "city": "AL MADINAH...",
    "benefits": "['Salary','10000']",
    "contract": "عقد مؤقت",
    "positions": "0 / 40",
    "job_post_id": "FRAUD2025QUAL1012",
    "exper": "3 Years"
  },
  {
    "fraudulent": 1,
    "job_title": "طبيب أسنان",
    "job_date": "30/05/1444",
    "job_desc": "['فرصة ذهبية للعمل في بيئة احترافية.']",
    "job_tasks": "['   الرد على رسائل واتساب', '   حفظ ملفات بسيطة', '  ', '  ']",
    "comp_name": "مؤسسة النجاح الفوري",
    "comp_no": "5-532348",
    "comp_type": "غير ربحي",
    "comp_size": "متوسطة فئة أ",
    "eco_activity": "nan",
    "qualif": "ثانوية عامة",
    "region": "المنطقة الشرقية",
    "city": "AR RIYADH...",
    "benefits": "['Salary','50000']",
    "contract": "دوام كامل",
    "positions": "0 / 18",
    "job_post_id": "FRAUD2025QUAL1013",
    "exper": "0 Years"
  },
  {
    "fraudulent": 1,
    "job_title": "محلل بيانات",
    "job_date": "27/05/1444",
    "job_desc": "['عمل إداري بسيط لا يتطلب مؤهلات خاصة.']",
    "job_tasks": "['   الرد على رسائل واتساب', '   حفظ ملفات بسيطة', '  ', '  ']",
    "comp_name": "شركة الثروة السريعة",
    "comp_no": "1-432963",
    "comp_type": "حكومي سري",
    "comp_size": "كبيرة",
    "eco_activity": "nan",
    "qualif": "شهادة ثانوية",
    "region": "المدينة المنورة",
    "city": "AL MADINAH...",
    "benefits": "['Salary','40000']",
    "contract": "عقد مؤقت",
    "positions": "0 / 25",
    "job_post_id": "FRAUD2025QUAL1014",
    "exper": "5 Years"
  },
  {
    "fraudulent": 1,
    "job_title": "محامي",
    "job_date": "30/05/1444",
    "job_desc": "['مطلوب فورا - التواصل عبر الواتساب فقط.']",
    "job_tasks": "['   الرد على رسائل واتساب', '   حفظ ملفات بسيطة', '  ', '  ']",
    "comp_name": "شركة المال السهل",
    "comp_no": "4-288012",
    "comp_type": "حكومي سري",
    "comp_size": "كبيرة",
    "eco_activity": "nan",
    "qualif": "شهادة ابتدائية",
    "region": "الرياض",
    "city": "AL MADINAH...",
    "benefits": "['Salary','40000']",
    "contract": "دوام جزئي",
    "positions": "0 / 19",
    "job_post_id": "FRAUD2025QUAL1015",
    "exper": "1 Years"
  },
  {
    "fraudulent": 1,
    "job_title": "محلل بيانات",
    "job_date": "29/05/1444",
    "job_desc": "['وظيفة حكومية مرموقة - الرجاء إرسال السيرة عبر الجيميل.']",
    "job_tasks": "['   الرد على رسائل واتساب', '   حفظ ملفات بسيطة', '  ', '  ']",
    "comp_name": "شركة الثروة السريعة",
    "comp_no": "6-673336",
    "comp_type": "حكومي سري",
    "comp_size": "صغيرة فئة أ",
    "eco_activity": "nan",
    "qualif": "Bachelor",
    "region": "الرياض",
    "city": "AL MADINAH...",
    "benefits": "['Salary','50000']",
    "contract": "عقد مؤقت",
    "positions": "0 / 16",
    "job_post_id": "FRAUD2025QUAL1016",
    "exper": "0 Years"
  },
  {
    "fraudulent": 1,
    "job_title": "أخصائي موارد بشرية",
    "job_date": "29/05/1444",
    "job_desc": "['فرصة ذهبية للعمل في بيئة احترافية.']",
    "job_tasks": "['   كتابة محتوى', '   تصميم بسيط', '   رفع تقارير دورية', '  ', '  ']",
    "comp_name": "شركة المال السهل",
    "comp_no": "7-442496",
    "comp_type": "غير ربحي",
    "comp_size": "متوسطة فئة أ",
    "eco_activity": "nan",
    "qualif": "شهادة متوسطة",
    "region": "المدينة المنورة",
    "city": "AR RIYADH...",
    "benefits": "['Salary','10000']",
    "contract": "دوام كامل",
    "positions": "0 / 16",
    "job_post_id": "FRAUD2025QUAL1017",
    "exper": "3 Years"
  },
  {
    "fraudulent": 1,
    "job_title": "محلل مالي",
    "job_date": "28/05/1444",
    "job_desc": "['راتب عالي جدا بدون أي متطلبات إضافية.']",
    "job_tasks": "['   كتابة محتوى', '   تصميم بسيط', '   رفع تقارير دورية', '  ', '  ']",
    "comp_name": "شركة المال السهل",
    "comp_no": "5-771630",
    "comp_type": "حكومي سري",
    "comp_size": "كبيرة",
    "eco_activity": "nan",
    "qualif": "ثانوية عامة",
    "region": "الرياض",
    "city": "JEDDAH...",
    "benefits": "['Salary','10000']",
    "contract": "دوام جزئي",
    "positions": "0 / 1",
    "job_post_id": "FRAUD2025QUAL1018",
    "exper": "1 Years"
  },
  {
    "fraudulent": 1,
    "job_title": "محلل بيانات",
    "job_date": "27/05/1444",
    "job_desc": "['راتب عالي جدا بدون أي متطلبات إضافية.']",
    "job_tasks": "['   كتابة محتوى', '   تصميم بسيط', '   رفع تقارير دورية', '  ', '  ']",
    "comp_name": "شركة الثروة السريعة",
    "comp_no": "9-313496",
    "comp_type": "حكومي سري",
    "comp_size": "متوسطة فئة أ",
    "eco_activity": "nan",
    "qualif": "شهادة ابتدائية",
    "region": "المدينة المنورة",
    "city": "JEDDAH...",
    "benefits": "['Salary','20000']",
    "contract": "دوام جزئي",
    "positions": "0 / 7",
    "job_post_id": "FRAUD2025QUAL1019",
    "exper": "5 Years"
  },
  {
    "fraudulent": 1,
    "job_title": "مدير تنفيذي",
    "job_date": "28/05/1444",
    "job_desc": "['مطلوب فورا - التواصل عبر الواتساب فقط.']",
    "job_tasks": "['   كتابة محتوى', '   تصميم بسيط', '   رفع تقارير دورية', '  ', '  ']",
    "comp_name": "شركة الثروة السريعة",
    "comp_no": "2-964979",
    "comp_type": "حكومي سري",
    "comp_size": "متوسطة فئة أ",
    "eco_activity": "nan",
    "qualif": "ثانوية عامة",
    "region": "المدينة المنورة",
    "city": "AL MADINAH...",
    "benefits": "['Salary','20000']",
    "contract": "دوام كامل",
    "positions": "0 / 20",
    "job_post_id": "FRAUD2025QUAL1020",
    "exper": "0 Years"
  },
  {
    "fraudulent": 1,
    "job_title": "طبيب أسنان",
    "job_date": "28/05/1444",
    "job_desc": "['راتب عالي جدا بدون أي متطلبات إضافية.']",
    "job_tasks": "['   متابعة البريد', '   إعداد تقارير', '   الرد على مكالمات', '  ', '  ']",
    "comp_name": "شركة المال السهل",
    "comp_no": "2-415981",
    "comp_type": "حكومي سري",
    "comp_size": "متوسطة فئة أ",
    "eco_activity": "nan",
    "qualif": "ثانوية عامة",
    "region": "الرياض",
    "city": "AR RIYADH...",
    "benefits": "['Salary','50000']",
    "contract": "دوام كامل",
    "positions": "0 / 7",
    "job_post_id": "FRAUD2025QUAL1021",
    "exper": "0 Years"
  },
  {
    "fraudulent": 1,
    "job_title": "طبيب عام",
    "job_date": "30/05/1444",
    "job_desc": "['راتب عالي جدا بدون أي متطلبات إضافية.']",
    "job_tasks": "['   الرد على رسائل واتساب', '   حفظ ملفات بسيطة', '  ', '  ']",
    "comp_name": "مؤسسة النجاح الفوري",
    "comp_no": "3-168999",
    "comp_type": "حكومي سري",
    "comp_size": "كبيرة",
    "eco_activity": "nan",
    "qualif": "شهادة ثانوية",
    "region": "المدينة المنورة",
    "city": "JEDDAH...",
    "benefits": "['Salary','20000']",
    "contract": "دوام جزئي",
    "positions": "0 / 38",
    "job_post_id": "FRAUD2025QUAL1022",
    "exper": "5 Years"
  },
  {
    "fraudulent": 1,
    "job_title": "مدرس",
    "job_date": "27/05/1444",
    "job_desc": "['وظيفة حكومية مرموقة - الرجاء إرسال السيرة عبر الجيميل.']",
    "job_tasks": "['   الرد على رسائل واتساب', '   حفظ ملفات بسيطة', '  ', '  ']",
    "comp_name": "مؤسسة النجاح الفوري",
    "comp_no": "1-990993",
    "comp_type": "خاص",
    "comp_size": "صغيرة فئة أ",
    "eco_activity": "nan",
    "qualif": "شهادة ثانوية",
    "region": "مكة المكرمة",
    "city": "JEDDAH...",
    "benefits": "['Salary','10000']",
    "contract": "دوام جزئي",
    "positions": "0 / 36",
    "job_post_id": "FRAUD2025QUAL1023",
    "exper": "5 Years"
  },
  {
    "fraudulent": 1,
    "job_title": "مهندس برمجيات",
    "job_date": "29/05/1444",
    "job_desc": "['وظيفة حكومية مرموقة - الرجاء إرسال السيرة عبر الجيميل.']",
    "job_tasks": "['   الرد على رسائل واتساب', '   حفظ ملفات بسيطة', '  ', '  ']",
    "comp_name": "مؤسسة النجاح الفوري",
    "comp_no": "3-287497",
    "comp_type": "غير ربحي",
    "comp_size": "متوسطة فئة أ",
    "eco_activity": "nan",
    "qualif": "ثانوية عامة",
    "region": "المدينة المنورة",
    "city": "JEDDAH...",
    "benefits": "['Salary','50000']",
    "contract": "دوام جزئي",
    "positions": "0 / 33",
    "job_post_id": "FRAUD2025QUAL1024",
    "exper": "1 Years"
  },
  {
    "fraudulent": 1,
    "job_title": "محلل مالي",
    "job_date": "28/05/1444",
    "job_desc": "['راتب عالي جدا بدون أي متطلبات إضافية.']",
    "job_tasks": "['   الرد على رسائل واتساب', '   حفظ ملفات بسيطة', '  ', '  ']",
    "comp_name": "شركة الثروة السريعة",
    "comp_no": "8-369132",
    "comp_type": "حكومي سري",
    "comp_size": "كبيرة",
    "eco_activity": "nan",
    "qualif": "شهادة ثانوية",
    "region": "المنطقة الشرقية",
    "city": "JEDDAH...",
    "benefits": "['Salary','10000']",
    "contract": "دوام جزئي",
    "positions": "0 / 38",
    "job_post_id": "FRAUD2025QUAL1025",
    "exper": "0 Years"
  },
  {
    "fraudulent": 1,
    "job_title": "محامي",
    "job_date": "29/05/1444",
    "job_desc": "['وظيفة حكومية مرموقة - الرجاء إرسال السيرة عبر الجيميل.']",
    "job_tasks": "['   كتابة محتوى', '   تصميم بسيط', '   رفع تقارير دورية', '  ', '  ']",
    "comp_name": "شركة المال السهل",
    "comp_no": "2-273563",
    "comp_type": "حكومي سري",
    "comp_size": "كبيرة",
    "eco_activity": "nan",
    "qualif": "دبلوم متوسط",
    "region": "المنطقة الشرقية",
    "city": "AR RIYADH...",
    "benefits": "['Salary','40000']",
    "contract": "دوام جزئي",
    "positions": "0 / 13",
    "job_post_id": "FRAUD2025QUAL1026",
    "exper": "5 Years"
  },
  {
    "fraudulent": 1,
    "job_title": "طبيب عام",
    "job_date": "27/05/1444",
    "job_desc": "['عمل إداري بسيط لا يتطلب مؤهلات خاصة.']",
    "job_tasks": "['   الرد على رسائل واتساب', '   حفظ ملفات بسيطة', '  ', '  ']",
    "comp_name": "مؤسسة النجاح الفوري",
    "comp_no": "1-690192",
    "comp_type": "خاص",
    "comp_size": "صغيرة فئة أ",
    "eco_activity": "nan",
    "qualif": "شهادة ابتدائية",
    "region": "مكة المكرمة",
    "city": "AD DAMMAM...",
    "benefits": "['Salary','50000']",
    "contract": "عقد مؤقت",
    "positions": "0 / 8",
    "job_post_id": "FRAUD2025QUAL1027",
    "exper": "1 Years"
  },
  {
    "fraudulent": 1,
    "job_title": "مدير تنفيذي",
    "job_date": "28/05/1444",
    "job_desc": "['وظيفة حكومية مرموقة - الرجاء إرسال السيرة عبر الجيميل.']",
    "job_tasks": "['   الرد على رسائل واتساب', '   حفظ ملفات بسيطة', '  ', '  ']",
    "comp_name": "جهة حكومية سرية",
    "comp_no": "8-163369",
    "comp_type": "خاص",
    "comp_size": "صغيرة فئة أ",
    "eco_activity": "nan",
    "qualif": "ثانوية عامة",
    "region": "الرياض",
    "city": "AL MADINAH...",
    "benefits": "['Salary','50000']",
    "contract": "دوام كامل",
    "positions": "0 / 18",
    "job_post_id": "FRAUD2025QUAL1028",
    "exper": "5 Years"
  },
  {
    "fraudulent": 1,
    "job_title": "محاسب",
    "job_date": "30/05/1444",
    "job_desc": "['وظيفة حكومية مرموقة - الرجاء إرسال السيرة عبر الجيميل.']",
    "job_tasks": "['   متابعة البريد', '   إعداد تقارير', '   الرد على مكالمات', '  ', '  ']",
    "comp_name": "شركة الثروة السريعة",
    "comp_no": "5-432579",
    "comp_type": "خاص",
    "comp_size": "صغيرة فئة أ",
    "eco_activity": "nan",
    "qualif": "دبلوم متوسط",
    "region": "المدينة المنورة",
    "city": "AR RIYADH...",
    "benefits": "['Salary','20000']",
    "contract": "عقد مؤقت",
    "positions": "0 / 7",
    "job_post_id": "FRAUD2025QUAL1029",
    "exper": "3 Years"
  },
  {
    "fraudulent": 1,
    "job_title": "مدرس",
    "job_date": "27/05/1444",
    "job_desc": "['فرصة ذهبية للعمل في بيئة احترافية.']",
    "job_tasks": "['   كتابة محتوى', '   تصميم بسيط', '   رفع تقارير دورية', '  ', '  ']",
    "comp_name": "شركة المال السهل",
    "comp_no": "2-220813",
    "comp_type": "خاص",
    "comp_size": "كبيرة",
    "eco_activity": "nan",
    "qualif": "شهادة متوسطة",
    "region": "الرياض",
    "city": "AR RIYADH...",
    "benefits": "['Salary','10000']",
    "contract": "عقد مؤقت",
    "positions": "0 / 34",
    "job_post_id": "FRAUD2025QUAL1030",
    "exper": "0 Years"
  },
  {
    "fraudulent": 1,
    "job_title": "محلل مالي",
    "job_date": "29/05/1444",
    "job_desc": "['راتب عالي جدا بدون أي متطلبات إضافية.']",
    "job_tasks": "['   متابعة البريد', '   إعداد تقارير', '   الرد على مكالمات', '  ', '  ']",
    "comp_name": "شركة الثروة السريعة",
    "comp_no": "4-554493",
    "comp_type": "خاص",
    "comp_size": "كبيرة",
    "eco_activity": "nan",
    "qualif": "شهادة ثانوية",
    "region": "مكة المكرمة",
    "city": "AR RIYADH...",
    "benefits": "['Salary','30000']",
    "contract": "عقد مؤقت",
    "positions": "0 / 23",
    "job_post_id": "FRAUD2025QUAL1031",
    "exper": "1 Years"
  },
  {
    "fraudulent": 1,
    "job_title": "طبيب عام",
    "job_date": "29/05/1444",
    "job_desc": "['راتب عالي جدا بدون أي متطلبات إضافية.']",
    "job_tasks": "['   الرد على رسائل واتساب', '   حفظ ملفات بسيطة', '  ', '  ']",
    "comp_name": "مؤسسة النجاح الفوري",
    "comp_no": "8-856007",
    "comp_type": "غير ربحي",
    "comp_size": "صغيرة فئة أ",
    "eco_activity": "nan",
    "qualif": "دبلوم متوسط",
    "region": "الرياض",
    "city": "AR RIYADH...",
    "benefits": "['Salary','20000']",
    "contract": "عقد مؤقت",
    "positions": "0 / 21",
    "job_post_id": "FRAUD2025QUAL1032",
    "exper": "0 Years"
  },
  {
    "fraudulent": 1,
    "job_title": "مطور ويب",
    "job_date": "28/05/1444",
    "job_desc": "['راتب عالي جدا بدون أي متطلبات إضافية.']",
    "job_tasks": "['   كتابة محتوى', '   تصميم بسيط', '   رفع تقارير دورية', '  ', '  ']",
    "comp_name": "جهة حكومية سرية",
    "comp_no": "5-842751",
    "comp_type": "خاص",
    "comp_size": "متوسطة فئة أ",
    "eco_activity": "nan",
    "qualif": "Diploma",
    "region": "المنطقة الشرقية",
    "city": "AD DAMMAM...",
    "benefits": "['Salary','40000']",
    "contract": "دوام كامل",
    "positions": "0 / 25",
    "job_post_id": "FRAUD2025QUAL1033",
    "exper": "1 Years"
  },
  {
    "fraudulent": 1,
    "job_title": "محلل مالي",
    "job_date": "28/05/1444",
    "job_desc": "['راتب عالي جدا بدون أي متطلبات إضافية.']",
    "job_tasks": "['   متابعة البريد', '   إعداد تقارير', '   الرد على مكالمات', '  ', '  ']",
    "comp_name": "جهة حكومية سرية",
    "comp_no": "3-690753",
    "comp_type": "خاص",
    "comp_size": "متوسطة فئة أ",
    "eco_activity": "nan",
    "qualif": "شهادة ثانوية",
    "region": "مكة المكرمة",
    "city": "AL MADINAH...",
    "benefits": "['Salary','20000']",
    "contract": "دوام جزئي",
    "positions": "0 / 15",
    "job_post_id": "FRAUD2025QUAL1034",
    "exper": "0 Years"
  },
  {
    "fraudulent": 1,
    "job_title": "طبيب أسنان",
    "job_date": "29/05/1444",
    "job_desc": "['راتب عالي جدا بدون أي متطلبات إضافية.']",
    "job_tasks": "['   متابعة البريد', '   إعداد تقارير', '   الرد على مكالمات', '  ', '  ']",
    "comp_name": "شركة المال السهل",
    "comp_no": "4-733579",
    "comp_type": "غير ربحي",
    "comp_size": "متوسطة فئة أ",
    "eco_activity": "nan",
    "qualif": "Bachelor",
    "region": "مكة المكرمة",
    "city": "AD DAMMAM...",
    "benefits": "['Salary','40000']",
    "contract": "دوام كامل",
    "positions": "0 / 22",
    "job_post_id": "FRAUD2025QUAL1035",
    "exper": "5 Years"
  },
  {
    "fraudulent": 1,
    "job_title": "مدير تنفيذي",
    "job_date": "27/05/1444",
    "job_desc": "['فرصة ذهبية للعمل في بيئة احترافية.']",
    "job_tasks": "['   متابعة البريد', '   إعداد تقارير', '   الرد على مكالمات', '  ', '  ']",
    "comp_name": "شركة المال السهل",
    "comp_no": "1-667975",
    "comp_type": "حكومي سري",
    "comp_size": "صغيرة فئة أ",
    "eco_activity": "nan",
    "qualif": "Bachelor",
    "region": "المدينة المنورة",
    "city": "AR RIYADH...",
    "benefits": "['Salary','30000']",
    "contract": "دوام جزئي",
    "positions": "0 / 14",
    "job_post_id": "FRAUD2025QUAL1036",
    "exper": "5 Years"
  },
  {
    "fraudulent": 1,
    "job_title": "محلل مالي",
    "job_date": "30/05/1444",
    "job_desc": "['راتب عالي جدا بدون أي متطلبات إضافية.']",
    "job_tasks": "['   متابعة البريد', '   إعداد تقارير', '   الرد على مكالمات', '  ', '  ']",
    "comp_name": "شركة الثروة السريعة",
    "comp_no": "6-476239",
    "comp_type": "حكومي سري",
    "comp_size": "كبيرة",
    "eco_activity": "nan",
    "qualif": "شهادة متوسطة",
    "region": "المدينة المنورة",
    "city": "AL MADINAH...",
    "benefits": "['Salary','10000']",
    "contract": "دوام جزئي",
    "positions": "0 / 4",
    "job_post_id": "FRAUD2025QUAL1037",
    "exper": "0 Years"
  },
  {
    "fraudulent": 1,
    "job_title": "محامي",
    "job_date": "27/05/1444",
    "job_desc": "['مطلوب فورا - التواصل عبر الواتساب فقط.']",
    "job_tasks": "['   الرد على رسائل واتساب', '   حفظ ملفات بسيطة', '  ', '  ']",
    "comp_name": "شركة الثروة السريعة",
    "comp_no": "7-754253",
    "comp_type": "خاص",
    "comp_size": "كبيرة",
    "eco_activity": "nan",
    "qualif": "nan",
    "region": "الرياض",
    "city": "AR RIYADH...",
    "benefits": "['Salary','40000']",
    "contract": "دوام كامل",
    "positions": "0 / 25",
    "job_post_id": "FRAUD2025QUAL1038",
    "exper": "5 Years"
  },
  {
    "fraudulent": 1,
    "job_title": "محاسب",
    "job_date": "27/05/1444",
    "job_desc": "['مطلوب فورا - التواصل عبر الواتساب فقط.']",
    "job_tasks": "['   متابعة البريد', '   إعداد تقارير', '   الرد على مكالمات', '  ', '  ']",
    "comp_name": "مؤسسة النجاح الفوري",
    "comp_no": "3-372134",
    "comp_type": "حكومي سري",
    "comp_size": "صغيرة فئة أ",
    "eco_activity": "nan",
    "qualif": "شهادة ابتدائية",
    "region": "المدينة المنورة",
    "city": "JEDDAH...",
    "benefits": "['Salary','20000']",
    "contract": "عقد مؤقت",
    "positions": "0 / 23",
    "job_post_id": "FRAUD2025QUAL1039",
    "exper": "5 Years"
  },
  {
    "fraudulent": 1,
    "job_title": "أخصائي موارد بشرية",
    "job_date": "29/05/1444",
    "job_desc": "['مطلوب فورا - التواصل عبر الواتساب فقط.']",
    "job_tasks": "['   الرد على رسائل واتساب', '   حفظ ملفات بسيطة', '  ', '  ']",
    "comp_name": "جهة حكومية سرية",
    "comp_no": "3-321182",
    "comp_type": "خاص",
    "comp_size": "كبيرة",
    "eco_activity": "nan",
    "qualif": "شهادة متوسطة",
    "region": "المدينة المنورة",
    "city": "AD DAMMAM...",
    "benefits": "['Salary','40000']",
    "contract": "دوام جزئي",
    "positions": "0 / 22",
    "job_post_id": "FRAUD2025QUAL1040",
    "exper": "5 Years"
  },
  {
    "fraudulent": 1,
    "job_title": "مدير مالي",
    "job_date": "30/05/1444",
    "job_desc": "['وظيفة حكومية مرموقة - الرجاء إرسال السيرة عبر الجيميل.']",
    "job_tasks": "['   الرد على رسائل واتساب', '   حفظ ملفات بسيطة', '  ', '  ']",
    "comp_name": "مؤسسة النجاح الفوري",
    "comp_no": "3-783039",
    "comp_type": "خاص",
    "comp_size": "صغيرة فئة أ",
    "eco_activity": "nan",
    "qualif": "شهادة متوسطة",
    "region": "الرياض",
    "city": "AD DAMMAM...",
    "benefits": "['Salary','30000']",
    "contract": "دوام كامل",
    "positions": "0 / 32",
    "job_post_id": "FRAUD2025QUAL1041",
    "exper": "5 Years"
  },
  {
    "fraudulent": 1,
    "job_title": "محلل مالي",
    "job_date": "28/05/1444",
    "job_desc": "['عمل إداري بسيط لا يتطلب مؤهلات خاصة.']",
    "job_tasks": "['   الرد على رسائل واتساب', '   حفظ ملفات بسيطة', '  ', '  ']",
    "comp_name": "شركة المال السهل",
    "comp_no": "5-758485",
    "comp_type": "حكومي سري",
    "comp_size": "كبيرة",
    "eco_activity": "nan",
    "qualif": "شهادة متوسطة",
    "region": "الرياض",
    "city": "AL MADINAH...",
    "benefits": "['Salary','15000']",
    "contract": "دوام كامل",
    "positions": "0 / 28",
    "job_post_id": "FRAUD2025QUAL1042",
    "exper": "0 Years"
  },
  {
    "fraudulent": 1,
    "job_title": "طبيب أسنان",
    "job_date": "28/05/1444",
    "job_desc": "['وظيفة حكومية مرموقة - الرجاء إرسال السيرة عبر الجيميل.']",
    "job_tasks": "['   كتابة محتوى', '   تصميم بسيط', '   رفع تقارير دورية', '  ', '  ']",
    "comp_name": "شركة المال السهل",
    "comp_no": "1-610018",
    "comp_type": "حكومي سري",
    "comp_size": "كبيرة",
    "eco_activity": "nan",
    "qualif": "ثانوية عامة",
    "region": "المنطقة الشرقية",
    "city": "AD DAMMAM...",
    "benefits": "['Salary','10000']",
    "contract": "دوام كامل",
    "positions": "0 / 11",
    "job_post_id": "FRAUD2025QUAL1043",
    "exper": "1 Years"
  },
  {
    "fraudulent": 1,
    "job_title": "محلل بيانات",
    "job_date": "28/05/1444",
    "job_desc": "['وظيفة حكومية مرموقة - الرجاء إرسال السيرة عبر الجيميل.']",
    "job_tasks": "['   متابعة البريد', '   إعداد تقارير', '   الرد على مكالمات', '  ', '  ']",
    "comp_name": "مؤسسة النجاح الفوري",
    "comp_no": "6-600300",
    "comp_type": "خاص",
    "comp_size": "كبيرة",
    "eco_activity": "nan",
    "qualif": "nan",
    "region": "المدينة المنورة",
    "city": "AL MADINAH...",
    "benefits": "['Salary','20000']",
    "contract": "دوام جزئي",
    "positions": "0 / 37",
    "job_post_id": "FRAUD2025QUAL1044",
    "exper": "5 Years"
  },
  {
    "fraudulent": 1,
    "job_title": "محلل بيانات",
    "job_date": "28/05/1444",
    "job_desc": "['عمل إداري بسيط لا يتطلب مؤهلات خاصة.']",
    "job_tasks": "['   كتابة محتوى', '   تصميم بسيط', '   رفع تقارير دورية', '  ', '  ']",
    "comp_name": "جهة حكومية سرية",
    "comp_no": "5-767111",
    "comp_type": "خاص",
    "comp_size": "كبيرة",
    "eco_activity": "nan",
    "qualif": "دبلوم متوسط",
    "region": "المدينة المنورة",
    "city": "AD DAMMAM...",
    "benefits": "['Salary','15000']",
    "contract": "دوام جزئي",
    "positions": "0 / 39",
    "job_post_id": "FRAUD2025QUAL1045",
    "exper": "1 Years"
  },
  {
    "fraudulent": 1,
    "job_title": "مدرس",
    "job_date": "29/05/1444",
    "job_desc": "['مطلوب فورا - التواصل عبر الواتساب فقط.']",
    "job_tasks": "['   متابعة البريد', '   إعداد تقارير', '   الرد على مكالمات', '  ', '  ']",
    "comp_name": "مؤسسة النجاح الفوري",
    "comp_no": "4-634961",
    "comp_type": "حكومي سري",
    "comp_size": "كبيرة",
    "eco_activity": "nan",
    "qualif": "nan",
    "region": "المنطقة الشرقية",
    "city": "AL MADINAH...",
    "benefits": "['Salary','10000']",
    "contract": "دوام جزئي",
    "positions": "0 / 35",
    "job_post_id": "FRAUD2025QUAL1046",
    "exper": "0 Years"
  },
  {
    "fraudulent": 1,
    "job_title": "أخصائي موارد بشرية",
    "job_date": "30/05/1444",
    "job_desc": "['راتب عالي جدا بدون أي متطلبات إضافية.']",
    "job_tasks": "['   الرد على رسائل واتساب', '   حفظ ملفات بسيطة', '  ', '  ']",
    "comp_name": "مؤسسة النجاح الفوري",
    "comp_no": "1-788058",
    "comp_type": "خاص",
    "comp_size": "متوسطة فئة أ",
    "eco_activity": "nan",
    "qualif": "شهادة متوسطة",
    "region": "المدينة المنورة",
    "city": "AL MADINAH...",
    "benefits": "['Salary','40000']",
    "contract": "عقد مؤقت",
    "positions": "0 / 11",
    "job_post_id": "FRAUD2025QUAL1047",
    "exper": "1 Years"
  },
  {
    "fraudulent": 1,
    "job_title": "مهندس برمجيات",
    "job_date": "27/05/1444",
    "job_desc": "['راتب عالي جدا بدون أي متطلبات إضافية.']",
    "job_tasks": "['   متابعة البريد', '   إعداد تقارير', '   الرد على مكالمات', '  ', '  ']",
    "comp_name": "مؤسسة النجاح الفوري",
    "comp_no": "1-168546",
    "comp_type": "خاص",
    "comp_size": "متوسطة فئة أ",
    "eco_activity": "nan",
    "qualif": "شهادة ثانوية",
    "region": "مكة المكرمة",
    "city": "AD DAMMAM...",
    "benefits": "['Salary','10000']",
    "contract": "دوام كامل",
    "positions": "0 / 18",
    "job_post_id": "FRAUD2025QUAL1048",
    "exper": "3 Years"
  },
  {
    "fraudulent": 1,
    "job_title": "مطور ويب",
    "job_date": "28/05/1444",
    "job_desc": "['وظيفة حكومية مرموقة - الرجاء إرسال السيرة عبر الجيميل.']",
    "job_tasks": "['   كتابة محتوى', '   تصميم بسيط', '   رفع تقارير دورية', '  ', '  ']",
    "comp_name": "شركة الثروة السريعة",
    "comp_no": "3-890924",
    "comp_type": "خاص",
    "comp_size": "صغيرة فئة أ",
    "eco_activity": "nan",
    "qualif": "ثانوية عامة",
    "region": "المدينة المنورة",
    "city": "JEDDAH...",
    "benefits": "['Salary','15000']",
    "contract": "عقد مؤقت",
    "positions": "0 / 20",
    "job_post_id": "FRAUD2025QUAL1049",
    "exper": "5 Years"
  }
]